{
    "app_name": "Basic Redis caching example in Nodejs",
    "description": "Showcases how to impliment caching in NodeJS",
    "type": "Building Block", // "Building Block" or "Full App"
    "contributed_by": "Redis Labs", // "Redis Labs" or "Community" or "Partner"
    "repo_url": "https://github.com/redis-developer/basic-caching-demo-nodejs", //Github URL
    "download_url": "https://github.com/redis-developer/basic-caching-demo-nodejs/archive/main.zip", //Direct download link
    "hosted_url": "", //If the app is hosted somewhere, enter it's url so people can interact with it
    "quick_deploy": "true", //Do we have Deploy to Heroku or Vercel etc buttons?
    "deploy_buttons": [
        {"heroku": "https://heroku.com/deploy?template=https://github.com/redis-developer/basic-caching-demo-nodejs"},
        {"vercel": "https://vercel.com/new/git/external?repository-url=https%3A%2F%2Fgithub.com%2Fredis-developer%2Fbasic-caching-demo-nodejs&env=REDIS_ENDPOINT_URI,REDIS_PASSWORD&envDescription=REDIS_ENDPOINT_URI%20is%20required%20at%20least%20to%20connect%20to%20Redis%20clouding%20server"},
        {"Google": "https://deploy.cloud.run/?git_repo=https://github.com/redis-developer/basic-caching-demo-nodejs.git"}
    ],
    "language": "JavaScript",
    "redis_commands": ["SETEX"], //List all the Redis commands used
    "redis_features": ["caching"], //List all the features used
    "redis_modules": [], //List the Redis modules used if any
    "app_image_urls":["https://github.com/redis-developer/basic-caching-demo-nodejs/blob/main/docs/screenshot001.png?raw=true"], //contains one or more images,
    "youtube_url": "", //show any Youtube URL
    "special_tags": [] //Any additional or special tags for filtering purposes like "Hackathon" or "Paid" etc  
}